MANIFEST.in
README.md
setup.py
wings_sanic/__init__.py
wings_sanic/app.py
wings_sanic/application.py
wings_sanic/blueprints.py
wings_sanic/datetime_helper.py
wings_sanic/event.py
wings_sanic/log_formatter.py
wings_sanic/metadata.py
wings_sanic/mq_server.py
wings_sanic/serializers.py
wings_sanic/settings.py
wings_sanic/template_main.py
wings_sanic/utils.py
wings_sanic/views.py
wings_sanic.egg-info/PKG-INFO
wings_sanic.egg-info/SOURCES.txt
wings_sanic.egg-info/dependency_links.txt
wings_sanic.egg-info/requires.txt
wings_sanic.egg-info/top_level.txt
wings_sanic/mq_servers/__init__.py
wings_sanic/mq_servers/rabbitmq_server.py
wings_sanic/swagger/__init__.py
wings_sanic/swagger/favicon-16x16.png
wings_sanic/swagger/favicon-32x32.png
wings_sanic/swagger/index.html
wings_sanic/swagger/openapi.py