Metadata-Version: 1.1
Name: wings-sanic
Version: 0.5.22
Summary: The wings-sanic is a lightweight python framework aimed at making it as simple as possible to document your Sanic API with Swagger UI, Plus param validation and model serialization.
Home-page: https://github.com/songtao-git/wings-sanic
Author: SongTao
Author-email: songtao@klicen.com
License: UNKNOWN
Platform: UNKNOWN
Classifier: Development Status :: 5 - Production/Stable
Classifier: Operating System :: MacOS
Classifier: Operating System :: POSIX :: Linux
Classifier: Topic :: System :: Software Distribution
Classifier: License :: OSI Approved :: MIT License
Classifier: Programming Language :: Python :: 3.7
